airflow/providers/fab/__init__.py
airflow/providers/fab/alembic.ini
airflow/providers/fab/get_provider_info.py
airflow/providers/fab/version_compat.py
airflow/providers/fab/auth_manager/__init__.py
airflow/providers/fab/auth_manager/fab_auth_manager.py
airflow/providers/fab/auth_manager/api/__init__.py
airflow/providers/fab/auth_manager/api/auth/__init__.py
airflow/providers/fab/auth_manager/api/auth/backend/__init__.py
airflow/providers/fab/auth_manager/api/auth/backend/basic_auth.py
airflow/providers/fab/auth_manager/api/auth/backend/kerberos_auth.py
airflow/providers/fab/auth_manager/api/auth/backend/session.py
airflow/providers/fab/auth_manager/api_endpoints/__init__.py
airflow/providers/fab/auth_manager/api_endpoints/role_and_permission_endpoint.py
airflow/providers/fab/auth_manager/api_endpoints/user_endpoint.py
airflow/providers/fab/auth_manager/api_fastapi/__init__.py
airflow/providers/fab/auth_manager/api_fastapi/parameters.py
airflow/providers/fab/auth_manager/api_fastapi/security.py
airflow/providers/fab/auth_manager/api_fastapi/sorting.py
airflow/providers/fab/auth_manager/api_fastapi/datamodels/__init__.py
airflow/providers/fab/auth_manager/api_fastapi/datamodels/login.py
airflow/providers/fab/auth_manager/api_fastapi/datamodels/roles.py
airflow/providers/fab/auth_manager/api_fastapi/openapi/__init__.py
airflow/providers/fab/auth_manager/api_fastapi/openapi/v2-fab-auth-manager-generated.yaml
airflow/providers/fab/auth_manager/api_fastapi/routes/__init__.py
airflow/providers/fab/auth_manager/api_fastapi/routes/login.py
airflow/providers/fab/auth_manager/api_fastapi/routes/roles.py
airflow/providers/fab/auth_manager/api_fastapi/services/__init__.py
airflow/providers/fab/auth_manager/api_fastapi/services/login.py
airflow/providers/fab/auth_manager/api_fastapi/services/roles.py
airflow/providers/fab/auth_manager/cli_commands/__init__.py
airflow/providers/fab/auth_manager/cli_commands/db_command.py
apache_airflow_providers_fab-3.1.2.dist-info/entry_points.txt
apache_airflow_providers_fab-3.1.2.dist-info/licenses/3rd-party-licenses/LICENSES-ui.txt
apache_airflow_providers_fab-3.1.2.dist-info/licenses/LICENSE
apache_airflow_providers_fab-3.1.2.dist-info/licenses/NOTICE
apache_airflow_providers_fab-3.1.2.dist-info/WHEEL
apache_airflow_providers_fab-3.1.2.dist-info/METADATA
apache_airflow_providers_fab-3.1.2.dist-info/RECORD
