Metadata-Version: 2.4
Name: apache-airflow-providers-fab
Version: 3.1.2
Summary: Provider package apache-airflow-providers-fab for Apache Airflow
Keywords: airflow-provider,fab,airflow,integration
Author-email: Apache Software Foundation <dev@airflow.apache.org>
Maintainer-email: Apache Software Foundation <dev@airflow.apache.org>
Requires-Python: >=3.10,!=3.13
License-Expression: Apache-2.0
Classifier: Development Status :: 5 - Production/Stable
Classifier: Environment :: Console
Classifier: Environment :: Web Environment
Classifier: Intended Audience :: Developers
Classifier: Intended Audience :: System Administrators
Classifier: Framework :: Apache Airflow
Classifier: Framework :: Apache Airflow :: Provider
Classifier: Programming Language :: Python :: 3.10
Classifier: Programming Language :: Python :: 3.11
Classifier: Programming Language :: Python :: 3.12
Classifier: Topic :: System :: Monitoring
License-File: 3rd-party-licenses/LICENSES-ui.txt
License-File: LICENSE
License-File: NOTICE
Requires-Dist: apache-airflow>=3.0.2
Requires-Dist: apache-airflow-providers-common-compat>=1.12.0
Requires-Dist: blinker>=1.6.2; python_version < '3.13'
Requires-Dist: flask>=2.2.1,<2.3; python_version < '3.13'
Requires-Dist: flask-appbuilder==5.0.1; python_version < '3.13'
Requires-Dist: flask-login>=0.6.2; python_version < '3.13'
Requires-Dist: flask-session>=0.8.0; python_version < '3.13'
Requires-Dist: msgpack>=1.0.0; python_version < '3.13'
Requires-Dist: flask-sqlalchemy>=3.0.5; python_version < '3.13'
Requires-Dist: flask-wtf>=1.1.0; python_version < '3.13'
Requires-Dist: connexion[flask]>=2.14.2,<3.0; python_version < '3.13'
Requires-Dist: jmespath>=0.7.0; python_version < '3.13'
Requires-Dist: werkzeug>=2.2,<4; python_version < '3.13'
Requires-Dist: wtforms>=3.0,<4; python_version < '3.13'
Requires-Dist: flask_limiter>3,<4,!=3.13
Requires-Dist: kerberos>=1.3.0 ; extra == "kerberos" and ( python_version < '3.13')
Project-URL: Bug Tracker, https://github.com/apache/airflow/issues
Project-URL: Changelog, https://airflow.apache.org/docs/apache-airflow-providers-fab/3.1.2/changelog.html
Project-URL: Documentation, https://airflow.apache.org/docs/apache-airflow-providers-fab/3.1.2
Project-URL: Mastodon, https://fosstodon.org/@airflow
Project-URL: Slack Chat, https://s.apache.org/airflow-slack
Project-URL: Source Code, https://github.com/apache/airflow
Project-URL: YouTube, https://www.youtube.com/channel/UCSXwxpWZQ7XZ1WL3wqevChA/
Provides-Extra: kerberos
